Tests/__init__.py
Tests/test_general.py
sslcommerz_python_api/__init__.py
sslcommerz_python_api/base.py
sslcommerz_python_api/payment.py
sslcommerz_python_api/validation.py
sslcommerz_python_api-0.0.9.dist-info/LICENSE
sslcommerz_python_api-0.0.9.dist-info/METADATA
sslcommerz_python_api-0.0.9.dist-info/WHEEL
sslcommerz_python_api-0.0.9.dist-info/top_level.txt
sslcommerz_python_api-0.0.9.dist-info/RECORD
