Metadata-Version: 2.1
Name: sslcommerz-python-api
Version: 0.0.9
Summary: Implements SSLCOMMERZ payment gateway in python based web apps.
Home-page: https://github.com/dreygur/SSLCommerz-Python-api
Author: Rakibul Yeasin
Author-email: ryeasin03@gmail.com
License: UNKNOWN
Platform: UNKNOWN
Classifier: Programming Language :: Python :: 3
Classifier: License :: OSI Approved :: MIT License
Classifier: Operating System :: OS Independent
Requires-Python: >=3.6
License-File: LICENSE
Requires-Dist: certifi (==2021.5.30)
Requires-Dist: charset-normalizer (==2.0.6)
Requires-Dist: idna (==3.2)
Requires-Dist: requests (==2.26.0)
Requires-Dist: sslcommerz-python-api (==0.0.7)
Requires-Dist: urllib3 (==1.26.7)
Requires-Dist: uuid (==1.30)
